toolkits/__init__.py
toolkits/setup.py
toolkits/cluster/__init__.py
toolkits/cluster/fc.py
toolkits/cluster/hv.py
toolkits/cluster/nearc.py
toolkits/cluster/nsse.py
toolkits/cluster/sse.py
toolkits/pprint/__init__.py
toolkits/pprint/pred.py
toolkits/tests/__init__.py
toolkits/utils/__init__.py
toolkits/utils/fm.py
toolkits/viz/__init__.py
toolkits/viz/tsne.py
dl_toolkits-1.0.1.2.dist-info/METADATA
dl_toolkits-1.0.1.2.dist-info/WHEEL
dl_toolkits-1.0.1.2.dist-info/top_level.txt
dl_toolkits-1.0.1.2.dist-info/RECORD
