Metadata-Version: 2.1
Name: dl-toolkits
Version: 1.0.1.2
Summary: Deep Learning Analysis Toolkits
Home-page: https://github.com/yuhodots/toolkits
Author: ['Yuho Jeong', 'Solang Kim']
License: UNKNOWN
Keywords: dl,toolkits
Platform: UNKNOWN
Requires-Python: >=3
